pyapollo/__init__.py
pyapollo/apollo_client.py
pyapollo/exceptions.py
apollo_client3-1.0.12.dist-info/METADATA
apollo_client3-1.0.12.dist-info/WHEEL
apollo_client3-1.0.12.dist-info/top_level.txt
apollo_client3-1.0.12.dist-info/RECORD
