Metadata-Version: 2.1
Name: apollo-client3
Version: 1.0.12
Summary: apollo-client升级到python3.10
Home-page: https://gitee.com/liujiguo_1_0/pyapollo-client3
Author: Johnliu
Author-email: 1242108463@qq.com
License: MIT
Platform: UNKNOWN
Classifier: Development Status :: 3 - Alpha
Classifier: Intended Audience :: Developers
Classifier: License :: OSI Approved :: MIT License
Classifier: Programming Language :: Python
Classifier: Programming Language :: Python :: 3.7
Classifier: Programming Language :: Python :: 3.10
